image_resizing_png/__init__.py
image_resizing_png/resizing.py
resizingNtoPNGconvt_daun-1.0.0.dist-info/LICENSE
resizingNtoPNGconvt_daun-1.0.0.dist-info/METADATA
resizingNtoPNGconvt_daun-1.0.0.dist-info/WHEEL
resizingNtoPNGconvt_daun-1.0.0.dist-info/top_level.txt
resizingNtoPNGconvt_daun-1.0.0.dist-info/RECORD
